setup.py
z0lib/LICENSE
z0lib/__init__.py
z0lib/__main__.py
z0lib/xuname
z0lib/z0librc
z0lib/z0librun.py
z0lib.egg-info/PKG-INFO
z0lib.egg-info/SOURCES.txt
z0lib.egg-info/dependency_links.txt
z0lib.egg-info/entry_points.txt
z0lib.egg-info/not-zip-safe
z0lib.egg-info/requires.txt
z0lib.egg-info/top_level.txt
z0lib/docs/MAINPAGE.rst
z0lib/docs/Makefile
z0lib/docs/conf.py
z0lib/docs/index.rst
z0lib/docs/logozero_180x46.png
z0lib/docs/readthedocs.yml
z0lib/docs/requirements.txt
z0lib/docs/rtd_changelog.rst
z0lib/docs/rtd_credits.rst
z0lib/docs/rtd_description.rst
z0lib/docs/rtd_features.rst
z0lib/docs/rtd_getting_started.rst
z0lib/egg-info/CHANGELOG.rst
z0lib/egg-info/DESCRIPTION.rst
z0lib/egg-info/FEATURES.csv
z0lib/scripts/__init__.py
z0lib/scripts/main.py
z0lib/tests/__init__.py
z0lib/tests/test.conf.sample
z0lib/tests/test_cfg1
z0lib/tests/test_cfg2
z0lib/tests/test_cfg3
z0lib/tests/test_cfg4
z0lib/tests/test_dict1
z0lib/tests/test_findpkg
z0lib/tests/test_package.py
z0lib/tests/test_parse_url
z0lib/tests/test_parseoptargs
z0lib/tests/test_run
z0lib/tests/test_run_traced.py
z0lib/tests/test_z0lib.py
z0lib/tests/tmp.py
z0lib/tests/tmp1.py
z0lib/tests/logs/_travis.yml
z0lib/tests/logs/z0lib_travis.yml